monads/__init__.py
monads/applicative.py
monads/currying.py
monads/fastapi.py
monads/functor.py
monads/future.py
monads/list.py
monads/maybe.py
monads/monad.py
monads/monoid.py
monads/py.typed
monads/reader.py
monads/result.py
monads/set.py
typed_monads-0.4.8.dist-info/LICENSE
typed_monads-0.4.8.dist-info/METADATA
typed_monads-0.4.8.dist-info/WHEEL
typed_monads-0.4.8.dist-info/top_level.txt
typed_monads-0.4.8.dist-info/RECORD
