Metadata-Version: 2.1
Name: typed-monads
Version: 0.4.8
Summary: Type-annotated monad implementations for Python 3.7+
Home-page: https://github.com/sammyrulez/typed-monads
Author: Correl Roush, Sam Reghenzi
Author-email: correl@gmail.com, sammyrulez@gmail.com
Classifier: Development Status :: 4 - Beta
Classifier: Intended Audience :: Developers
Classifier: License :: OSI Approved :: MIT License
Classifier: Operating System :: OS Independent
Classifier: Programming Language :: Python :: 3 :: Only
Classifier: Programming Language :: Python :: 3.7
Classifier: Programming Language :: Python :: 3.8
Classifier: Programming Language :: Python :: 3.9
Classifier: Topic :: Software Development :: Libraries
License-File: LICENSE
